sendook_mcp.py
sendook_mcp-1.0.0.dist-info/METADATA
sendook_mcp-1.0.0.dist-info/WHEEL
sendook_mcp-1.0.0.dist-info/entry_points.txt
sendook_mcp-1.0.0.dist-info/RECORD
