Metadata-Version: 2.4
Name: sendook-mcp
Version: 1.0.0
Summary: MCP Server for Sendook - AI Email Communication Platform
Project-URL: Homepage, https://www.sendook.com
Project-URL: Repository, https://github.com/StreamlinedStartup/sendook-mcp
Project-URL: Documentation, https://github.com/StreamlinedStartup/sendook-mcp#readme
Project-URL: Issues, https://github.com/StreamlinedStartup/sendook-mcp/issues
Author-email: The Streamlined Startup <hello@sendook.com>
License-Expression: MIT
Keywords: ai-agents,claude,email,mcp,model-context-protocol,sendook
Classifier: Development Status :: 4 - Beta
Classifier: Intended Audience :: Developers
Classifier: License :: OSI Approved :: MIT License
Classifier: Programming Language :: Python :: 3
Classifier: Programming Language :: Python :: 3.10
Classifier: Programming Language :: Python :: 3.11
Classifier: Programming Language :: Python :: 3.12
Classifier: Programming Language :: Python :: 3.13
Classifier: Topic :: Communications :: Email
Classifier: Topic :: Software Development :: Libraries :: Python Modules
Requires-Python: >=3.10
Requires-Dist: httpx>=0.27.0
Requires-Dist: mcp>=1.0.0
Requires-Dist: pydantic>=2.0.0
Provides-Extra: dev
Requires-Dist: pytest-asyncio>=0.23.0; extra == 'dev'
Requires-Dist: pytest>=8.0.0; extra == 'dev'
Requires-Dist: ruff>=0.3.0; extra == 'dev'
